{"comment": "Amulya", "completionNotification": {"command": "", "executeOn": "Ignore"}, "autoStartEnabled": true, "description": "Traditional Backup to pool Dev2_pool, with expiration 1 Months;", "restartTimeWindow": "12:00", "enabled": true, "actions": [{"comment": "Amulya", "completionNotification": {"command": "", "executeOn": "Ignore"}, "actionSpecificData": {"backup": {"overrideRetentionPeriod": true, "clientOverride": "ClientCanOverride", "destinationStorageNodes": ["nsrserverhost"], "retentionPeriod": "2 Month", "overrideBackupSchedule": false, "backupSpecificData": {"traditional": {"revertToFullWhenSyntheticFullFails": true, "timestampFormat": "None", "verifySyntheticFull": true, "destinationPool": "amulya", "estimate": false, "fileInactivityThresholdInDays": 0, "fileInactivityAlertThresholdPercentage": 0}}, "successThreshold": "Success"}}, "failureImpact": "Continue", "concurrent": true, "inactivityTimeoutInMin": 30, "schedulePeriod": "Month", "scheduleOverrides": [], "enabled": true, "hardLimit": "00:00", "retries": 1, "softLimit": "00:00", "drivenBy": "", "scheduleActivities": ["incr", "incr", "incr", "incr", "incr", "incr", "incr"], "parallelism": 100, "retryDelayInSec": 30, "name": "Backup"}], "nextStartDate": "2022-07-11T22:00:00-04:00", "protectionGroups": ["Bronze-Filesystem"], "startInterval": "24:00", "startTime": "21:00", "endTime": "21:00", "name": "Filesystem"}